gifu/__init__.py
gifu/__main__.py
gifu/gifuu.py
gifu-1.0.0.data/data/gifu/gifu.xbm
gifu-1.0.0.data/data/gifu/tekisuto.txt
gifu-1.0.0.dist-info/METADATA
gifu-1.0.0.dist-info/WHEEL
gifu-1.0.0.dist-info/entry_points.txt
gifu-1.0.0.dist-info/top_level.txt
gifu-1.0.0.dist-info/RECORD
