Metadata-Version: 2.1
Name: gifu
Version: 1.0.0
Summary: Usando um programa para traduzir, e criando baralhos para o anki
Home-page: https://github.com/narutolavo/gifu
Author: Narutolavo
Author-email: narutoolavo@outlook.com
License: MIT License
Keywords: traduzir,estudar,anki,ingles
Platform: UNKNOWN
Requires-Dist: googletrans (==4.0.0rc1)
